freneticlib/__init__.py
freneticlib/core/__init__.py
freneticlib/core/core.py
freneticlib/core/mutation/__init__.py
freneticlib/core/mutation/abstract_operators.py
freneticlib/core/mutation/crossovers.py
freneticlib/core/mutation/exploiters.py
freneticlib/core/mutation/mutators.py
freneticlib/core/objective.py
freneticlib/executors/__init__.py
freneticlib/executors/autonomoose/local_dev.py.txt
freneticlib/executors/beamng/__init__.py
freneticlib/executors/beamng/beamng_executor.py
freneticlib/executors/bicycle/LICENSE_CVC.MIT
freneticlib/executors/bicycle/NOTICE
freneticlib/executors/bicycle/__init__.py
freneticlib/executors/bicycle/agents/tools/misc.py
freneticlib/executors/bicycle/bicycleexecutor.py
freneticlib/executors/bicycle/carla.py
freneticlib/executors/bicycle/carlapidonbicycle.py
freneticlib/executors/bicycle/controller.py
freneticlib/executors/bicycle/testplotter.py
freneticlib/executors/bicycle/util.py
freneticlib/executors/bicycle/vehicle.py
freneticlib/executors/executor.py
freneticlib/executors/mock.py
freneticlib/executors/outcome.py
freneticlib/executors/road_validator.py
freneticlib/frenetic.py
freneticlib/representations/__init__.py
freneticlib/representations/abstract_representation.py
freneticlib/representations/bezier_representation.py
freneticlib/representations/cartesian_representation.py
freneticlib/representations/kappa_representation.py
freneticlib/representations/theta_representation.py
freneticlib/stopcriteria/__init__.py
freneticlib/stopcriteria/abstract.py
freneticlib/stopcriteria/counter.py
freneticlib/stopcriteria/timer.py
freneticlib/utils/__init__.py
freneticlib/utils/catmull.py
freneticlib/utils/gaussian.py
freneticlib/utils/geometry_utils.py
freneticlib/utils/random.py
freneticlib-1.0.dist-info/METADATA
freneticlib-1.0.dist-info/WHEEL
freneticlib-1.0.dist-info/RECORD
