Metadata-Version: 2.1
Name: freneticlib
Version: 1.0
Summary: The Frenetic algorithm for search-based ADS road generation
Home-page: https://github.com/ERATOMMSD/frenetic
License: MIT
Keywords: frenetic,search-based road generation
Author: Stefan Klikovits
Author-email: stefan@klikovits.net
Requires-Python: >=3.8,<4.0
Classifier: Intended Audience :: Developers
Classifier: Intended Audience :: Science/Research
Classifier: License :: OSI Approved :: MIT License
Classifier: Operating System :: OS Independent
Classifier: Programming Language :: Python :: 3
Classifier: Programming Language :: Python :: 3.8
Classifier: Programming Language :: Python :: 3.9
Classifier: Programming Language :: Python :: 3.10
Classifier: Programming Language :: Python :: 3.11
Classifier: Programming Language :: Python :: 3
Classifier: Topic :: Scientific/Engineering
Classifier: Topic :: Scientific/Engineering :: Artificial Intelligence
Classifier: Topic :: Scientific/Engineering :: Mathematics
Classifier: Typing :: Typed
Provides-Extra: test
Requires-Dist: beamngpy
Requires-Dist: bezier
Requires-Dist: click
Requires-Dist: matplotlib
Requires-Dist: numpy
Requires-Dist: pandas
Requires-Dist: pytest ; extra == "test"
Requires-Dist: scipy
Requires-Dist: shapely
Project-URL: Bug Tracker, https://github.com/ERATOMMSD/frenetic/issues
Project-URL: Documentation, https://github.com/ERATOMMSD/frenetic
Project-URL: Repository, https://github.com/ERATOMMSD/frenetic
